nacos/__init__.py
nacos/auth.py
nacos/client.py
nacos/commons.py
nacos/exception.py
nacos/files.py
nacos/listener.py
nacos/params.py
nacos/task.py
nacos/timer.py
v2/__init__.py
v2/nacos/__init__.py
v2/nacos/nacos_client.py
v2/nacos/common/__init__.py
v2/nacos/common/auth.py
v2/nacos/common/client_config.py
v2/nacos/common/client_config_builder.py
v2/nacos/common/constants.py
v2/nacos/common/nacos_exception.py
v2/nacos/common/payload_registry.py
v2/nacos/common/preserved_metadata_key.py
v2/nacos/config/__init__.py
v2/nacos/config/nacos_config_service.py
v2/nacos/config/cache/__init__.py
v2/nacos/config/cache/config_info_cache.py
v2/nacos/config/cache/config_subscribe_manager.py
v2/nacos/config/encryption/__init__.py
v2/nacos/config/encryption/kms_client.py
v2/nacos/config/encryption/kms_handler.py
v2/nacos/config/encryption/plugin/__init__.py
v2/nacos/config/encryption/plugin/encryption_plugin.py
v2/nacos/config/encryption/plugin/kms_aes_128_encrytion_plugin.py
v2/nacos/config/encryption/plugin/kms_aes_256_encrytion_plugin.py
v2/nacos/config/encryption/plugin/kms_base_encryption_plugin.py
v2/nacos/config/encryption/plugin/kms_encrytion_plugin.py
v2/nacos/config/filter/__init__.py
v2/nacos/config/filter/config_encryption_filter.py
v2/nacos/config/filter/config_filter.py
v2/nacos/config/model/__init__.py
v2/nacos/config/model/config.py
v2/nacos/config/model/config_param.py
v2/nacos/config/model/config_request.py
v2/nacos/config/model/config_response.py
v2/nacos/config/remote/__init__.py
v2/nacos/config/remote/config_change_notify_request_handler.py
v2/nacos/config/remote/config_grpc_client_proxy.py
v2/nacos/config/remote/config_grpc_connection_event_listener.py
v2/nacos/config/util/__init__.py
v2/nacos/config/util/config_client_util.py
v2/nacos/naming/__init__.py
v2/nacos/naming/nacos_naming_service.py
v2/nacos/naming/cache/__init__.py
v2/nacos/naming/cache/service_info_cache.py
v2/nacos/naming/cache/subscribe_manager.py
v2/nacos/naming/event/__init__.py
zgkj_nacos_sdk_python-1.0.0.dist-info/LICENSE
zgkj_nacos_sdk_python-1.0.0.dist-info/METADATA
zgkj_nacos_sdk_python-1.0.0.dist-info/WHEEL
zgkj_nacos_sdk_python-1.0.0.dist-info/top_level.txt
zgkj_nacos_sdk_python-1.0.0.dist-info/RECORD
