Metadata-Version: 2.2
Name: zgkj-nacos-sdk-python
Version: 1.0.0
Summary: Python client for Nacos.
Home-page: https://github.com/hellodeveye/nacos-sdk-python
Author: nacos
Author-email: deveye@126.com
License: Apache License 2.0
Project-URL: Documentation, https://github.com/nacos-group/nacos-sdk-python
Project-URL: Source, https://github.com/nacos-group/nacos-sdk-python
Project-URL: Nacos Open API Guide, https://nacos.io/en-us/docs/open-api.html
Keywords: nacos,nacos-sdk-python
Classifier: Topic :: Software Development :: Libraries :: Python Modules
Classifier: Operating System :: OS Independent
Classifier: Programming Language :: Python
Classifier: Programming Language :: Python :: 2.7
Classifier: Programming Language :: Python :: 3.6
Classifier: Programming Language :: Python :: 3.7
License-File: LICENSE
Requires-Dist: aiofiles>=24.1.0
Requires-Dist: aiohttp>=3.10.11
Requires-Dist: alibabacloud_kms20160120>=2.2.3
Requires-Dist: alibabacloud_tea_openapi>=0.3.12
Requires-Dist: grpcio>=1.66.1
Requires-Dist: protobuf>=3.20.3
Requires-Dist: psutil>=5.9.6
Requires-Dist: pycryptodome>=3.19.1
Requires-Dist: pydantic>=2.10.4
Dynamic: author
Dynamic: author-email
Dynamic: classifier
Dynamic: description
Dynamic: description-content-type
Dynamic: home-page
Dynamic: keywords
Dynamic: license
Dynamic: project-url
Dynamic: requires-dist
Dynamic: summary
